piicleaner-0.4.1.dist-info/METADATA
piicleaner-0.4.1.dist-info/WHEEL
piicleaner-0.4.1.dist-info/licenses/LICENSE
piicleaner/__init__.py
piicleaner/_cleaner.py
piicleaner/_internal.cpython-312-x86_64-linux-gnu.so
piicleaner/_internal.pyi
piicleaner/_pandas.py
piicleaner/_pandas_plugin.py
piicleaner/_polars.py
piicleaner/_polars_plugin.py
piicleaner/py.typed
piicleaner-0.4.1.dist-info/RECORD
