Metadata-Version: 2.4
Name: piicleaner
Version: 0.4.1
Classifier: Development Status :: 4 - Beta
Classifier: Intended Audience :: Developers
Classifier: License :: OSI Approved :: MIT License
Classifier: Programming Language :: Python :: 3
Classifier: Programming Language :: Python :: 3.9
Classifier: Programming Language :: Python :: 3.10
Classifier: Programming Language :: Python :: 3.11
Classifier: Programming Language :: Python :: 3.12
Classifier: Programming Language :: Python :: 3.13
Classifier: Programming Language :: Rust
Classifier: Topic :: Software Development :: Libraries :: Python Modules
Classifier: Topic :: Text Processing
Classifier: Topic :: Security
Requires-Dist: polars>=1.0.0 ; extra == 'polars'
Requires-Dist: pandas>=2.3.0 ; extra == 'pandas'
Provides-Extra: polars
Provides-Extra: pandas
License-File: LICENSE
Summary: Fast PII detection and cleaning for text data with Polars integration
Author-email: Hamed Bastan-Hagh <hamed@bastanhagh.com>
License: MIT
Requires-Python: >=3.10
Project-URL: Homepage, https://github.com/hamedbh/piicleaner
Project-URL: Repository, https://github.com/hamedbh/piicleaner
Project-URL: Issues, https://github.com/hamedbh/piicleaner/issues
